README.rst
setup.py
datacoco_sf_tools/__init__.py
datacoco_sf_tools/__version__.py
datacoco_sf_tools/sf_tools.py
datacoco_sf_tools.egg-info/PKG-INFO
datacoco_sf_tools.egg-info/SOURCES.txt
datacoco_sf_tools.egg-info/dependency_links.txt
datacoco_sf_tools.egg-info/requires.txt
datacoco_sf_tools.egg-info/top_level.txt