Metadata-Version: 1.1
Name: datacoco-sf-tools
Version: 0.1.0
Summary: Data common code for SF Interaction by Equinox
Home-page: https://github.com/equinoxfitness/datacoco-sf_tools
Author: Equinox Fitness
Author-email: UNKNOWN
License: MIT
Platform: UNKNOWN
Classifier: Development Status :: 5 - Production/Stable
Classifier: Intended Audience :: Developers
Classifier: Natural Language :: English
Classifier: License :: OSI Approved :: MIT License
Classifier: Programming Language :: Python :: 3.6
